{"estadoDoc":"Transmitido Satisfactoriamente","estadoDocInc":"SRO","reporteInc":false,"descripcionEstado":"Documento Recibido con Observaciones","fechaEmi":"2026-05-23","horaEmi":"09:50:32","fechaProcesado":"2026-05-27 09:50:32","codGen":"94C33B18-35A3-4589-8C62-D9B68FDD6408","selloVal":"202611C4525C4C234FAAA14FC04E2D454E12OIHZ","numeIdenRecep":"06143108051032","action":"OK","tipoDte":"03","nombDte":"COMPROBANTE DE CREDITO FISCAL","ajustes":[{"tipDteRef":"05","codigoGeneracionRef":"AC150EFF-E3D6-4FB8-A7D4-9339657B2415","numValidacionRef":"202695B5542C53E74802A17EBB13A2EB0F03HG6M","fecHorEmi":"Fri May 29 16:23:37 CST 2026"}],"observaciones":["[identificacion.fecEmi] DIFIERE DE LA FECHA DE ENVIO"],"documento":{"identificacion":{"fecEmi":"2026-05-23","horEmi":"09:50:32","numeroControl":"DTE-03-M001P001-000000000084478","version":3},"resumen":{"totalSujetoRetencion":null,"totalIVAretenido":null,"totalIvaRetenido":null,"totalIVAretenidoLetras":null,"valorTotal":null,"totalNoSuj":0,"descuNoSuj":0,"total":null,"totalIva":null,"totalLetras":"CINCUENTA Y SEIS CON 45/100 U.S. DOLARES","ivaPerci1":0,"ivaPerci":null,"ivaRete1":0,"ivaRete":null,"subTotalVentas":56.45,"subTotal":56.45,"reteRenta":0,"tributos":null,"pagos":null,"descuExenta":0,"totalDescu":0,"numPagoElectronico":null,"descuGravada":0,"procentajeDescuento":null,"totalGravada":0,"montoTotalOperacion":56.45,"totalNoGravado":0,"saldoFavor":0,"totalExenta":56.45,"totalPagar":56.45,"condicionOperacion":3},"cuerpoDocumento":[{"descripcion":"INTERESES CRED ROTATIVO CTA CT            ","tipoDonacion":null,"depreciacion":null,"valorUni":null,"valor":null,"tipoDte":null,"tipoDoc":null,"numDocumento":null,"fechaEmision":null,"montoSujetoGrav":null,"codigoRetencionMH":null,"ivaRetenido":null,"montoDescu":0,"ventaGravada":0,"codigo":null,"ivaItem":null,"ventaNoSuj":0,"ventaExenta":56.45,"tributos":null,"numItem":1,"noGravado":0,"psv":0,"codTributo":null,"tipoItem":2,"uniMedida":99,"cantidad":1,"precioUni":56.45,"ivaPercibido":null,"periodoLiquidacionFechaFin":null,"periodoLiquidacionFechaInicio":null,"ivaComision":null,"codLiquidacion":null,"totalLetras":null,"subTotal":null,"montoSujetoPercepcion":null,"descripSinPercepcion":null,"iva":null,"comision":null,"porcentComision":null,"observaciones":null,"cantidadDoc":null,"valorOperaciones":null,"liquidoApagar":null,"montoSinPercepcion":null}],"otrosDocumentos":null,"ventaTercero":null,"apendice":null,"documentoRelacionado":null},"invalidacion":null,"otroEvento":[]}